flake8_strings/__init__.py
flake8_strings/errors.py
flake8_strings/plugin.py
flake8_strings/visitor.py
flake8_strings-0.1.1.dist-info/entry_points.txt
flake8_strings-0.1.1.dist-info/LICENSE
flake8_strings-0.1.1.dist-info/WHEEL
flake8_strings-0.1.1.dist-info/METADATA
flake8_strings-0.1.1.dist-info/RECORD
