Metadata-Version: 2.1
Name: flake8-strings
Version: 0.1.1
Summary: Flake8 Linter for Strings
Home-page: https://pypi.org/project/flake8-strings
License: MIT
Author: David S
Author-email: d1618033@gmail.com
Requires-Python: >=3.6,<4.0
Classifier: License :: OSI Approved :: MIT License
Classifier: Programming Language :: Python :: 3
Classifier: Programming Language :: Python :: 3.6
Classifier: Programming Language :: Python :: 3.7
Classifier: Programming Language :: Python :: 3.8
Requires-Dist: flake8-plugin-utils
Project-URL: Repository, https://github.com/d1618033/flake8-strings
